omnix/__init__.py
omnix/__main__.py
omnix/main.py
omnix/models/__init__.py
omnix/models/base.py
omnix/models/settings.py
omnix/static/css/layout.css
omnix/static/images/down.png
omnix/static/images/equal.png
omnix/static/images/login.png
omnix/static/images/up.png
omnix/static/images/email/logo.png
omnix/static/js/main.js
omnix/templates/about.html.tpl
omnix/templates/error.html.tpl
omnix/templates/index.html.tpl
omnix/templates/signin.html.tpl
omnix/templates/top.html.tpl
omnix/templates/customer/list.html.tpl
omnix/templates/customer/show.html.tpl
omnix/templates/email/activity.en_us.html.tpl
omnix/templates/email/activity.pt_pt.html.tpl
omnix/templates/email/birthday.en_us.html.tpl
omnix/templates/email/birthday.pt_pt.html.tpl
omnix/templates/email/layout.en_us.html.tpl
omnix/templates/email/layout.pt_pt.html.tpl
omnix/templates/email/macros.html.tpl
omnix/templates/employee/list.html.tpl
omnix/templates/employee/sales.html.tpl
omnix/templates/employee/show.html.tpl
omnix/templates/entity/edit.html.tpl
omnix/templates/entity/list.html.tpl
omnix/templates/entity/show.html.tpl
omnix/templates/extra/browser.html.tpl
omnix/templates/extra/costs.html.tpl
omnix/templates/extra/ctt.html.tpl
omnix/templates/extra/images.html.tpl
omnix/templates/extra/inventory.html.tpl
omnix/templates/extra/list.html.tpl
omnix/templates/extra/media.html.tpl
omnix/templates/extra/metadata.html.tpl
omnix/templates/extra/prices.html.tpl
omnix/templates/extra/template.html.tpl
omnix/templates/extra/transfers.html.tpl
omnix/templates/extra/browser/new_media.html.tpl
omnix/templates/media/edit.html.tpl
omnix/templates/media/list.html.tpl
omnix/templates/media/show.html.tpl
omnix/templates/partials/content_type.html.tpl
omnix/templates/partials/doctype.html.tpl
omnix/templates/partials/end_doctype.html.tpl
omnix/templates/partials/footer.html.tpl
omnix/templates/partials/includes.html.tpl
omnix/templates/partials/layout.html.tpl
omnix/templates/partials/layout_employee.html.tpl
omnix-0.3.13.dist-info/METADATA
omnix-0.3.13.dist-info/WHEEL
omnix-0.3.13.dist-info/top_level.txt
omnix-0.3.13.dist-info/RECORD
