Metadata-Version: 2.1
Name: omnix
Version: 0.3.13
Summary: Omnix System
Home-page: http://omnix.hive.pt
Author: Hive Solutions Lda.
Author-email: development@hive.pt
License: Apache License, Version 2.0
Keywords: omni extensions erp
Platform: UNKNOWN
Classifier: Development Status :: 5 - Production/Stable
Classifier: Topic :: Utilities
Classifier: License :: OSI Approved :: Apache Software License
Classifier: Operating System :: OS Independent
Classifier: Programming Language :: Python
Classifier: Programming Language :: Python :: 2.6
Classifier: Programming Language :: Python :: 2.7
Classifier: Programming Language :: Python :: 3.0
Classifier: Programming Language :: Python :: 3.1
Classifier: Programming Language :: Python :: 3.2
Classifier: Programming Language :: Python :: 3.3
Classifier: Programming Language :: Python :: 3.4
Classifier: Programming Language :: Python :: 3.5
Classifier: Programming Language :: Python :: 3.6
Classifier: Programming Language :: Python :: 3.7
Requires-Dist: netius
Requires-Dist: flask
Requires-Dist: quorum
Requires-Dist: pillow
Requires-Dist: pymongo
Requires-Dist: redis
Requires-Dist: pika
Requires-Dist: xlrd
Requires-Dist: omni-api
